odoo/addons/stock_request_analytic/README.rst
odoo/addons/stock_request_analytic/__init__.py
odoo/addons/stock_request_analytic/__manifest__.py
odoo/addons/stock_request_analytic/i18n/es.po
odoo/addons/stock_request_analytic/i18n/it.po
odoo/addons/stock_request_analytic/i18n/pt_BR.po
odoo/addons/stock_request_analytic/i18n/stock_request_analytic.pot
odoo/addons/stock_request_analytic/i18n/zh_CN.po
odoo/addons/stock_request_analytic/migrations/16.0.1.0.0/post-migration.py
odoo/addons/stock_request_analytic/models/__init__.py
odoo/addons/stock_request_analytic/models/stock_request.py
odoo/addons/stock_request_analytic/models/stock_request_order.py
odoo/addons/stock_request_analytic/readme/CONTRIBUTORS.md
odoo/addons/stock_request_analytic/readme/DESCRIPTION.md
odoo/addons/stock_request_analytic/readme/ROADMAP.md
odoo/addons/stock_request_analytic/readme/USAGE.md
odoo/addons/stock_request_analytic/security/ir.model.access.csv
odoo/addons/stock_request_analytic/static/description/icon.png
odoo/addons/stock_request_analytic/static/description/index.html
odoo/addons/stock_request_analytic/tests/__init__.py
odoo/addons/stock_request_analytic/tests/test_stock_request_analytic.py
odoo/addons/stock_request_analytic/views/stock_request_order_views.xml
odoo/addons/stock_request_analytic/views/stock_request_views.xml
odoo_addon_stock_request_analytic-17.0.1.0.0.2.dist-info/METADATA
odoo_addon_stock_request_analytic-17.0.1.0.0.2.dist-info/WHEEL
odoo_addon_stock_request_analytic-17.0.1.0.0.2.dist-info/top_level.txt
odoo_addon_stock_request_analytic-17.0.1.0.0.2.dist-info/RECORD
